yze/__init__.py
yze/benchmark_mutant.py
yze/dice.py
yze/mutant_odds_of_pushing.py
yze-0.0.7.dist-info/METADATA
yze-0.0.7.dist-info/WHEEL
yze-0.0.7.dist-info/entry_points.txt
yze-0.0.7.dist-info/top_level.txt
yze-0.0.7.dist-info/RECORD
