Metadata-Version: 2.1
Name: yze
Version: 0.0.7
Summary: A small package to handle YZE games mechanics
Author-email: Nicolas Legrand <nicolas.legrand@gmail.com>
Project-URL: Homepage, https://github.com/nlegrand/yze
Project-URL: Bug Tracker, https://github.com/nlegrand/yze/issues
Classifier: Programming Language :: Python :: 3
Classifier: License :: OSI Approved :: ISC License (ISCL)
Classifier: Operating System :: OS Independent
Requires-Python: >=3.11
